{"metadata":{"uid":"0bb18300-097c-4733-bd61-52ac1f647b17","history":["2023-09-07T06:09:44; 0bb18300-097c-4733-bd61-52ac1f647b17; Generated from raw coverage data."]},"file":"/home/demo-user/sandbox/demo-project/iceoryx_master/iceoryx_hoofs/include/iceoryx_hoofs/internal/concurrent/lockfree_queue/lockfree_queue.inl","functions":[{"id":"_ZN3iox10concurrent13LockFreeQueueIT_mE7tryPushEOS2_","name":"iox::concurrent::LockFreeQueue<T1, unsigned long>::tryPush(T1 &&)","beginLine":0,"beginCol":0,"endLine":0,"endCol":0,"covered":false,"lines":[{"line":65,"covered":true},{"line":67,"covered":true},{"line":70,"covered":true},{"line":72,"covered":true},{"line":74,"covered":true},{"line":63,"covered":true}],"statements":[],"blocks":[],"conditions":[],"branchDecisions":[{"beginLine":65,"beginCol":9,"endLine":65,"endCol":33,"branches":[{"beginLine":67,"beginCol":9,"endLine":67,"endCol":21,"covered":true},{"beginLine":70,"beginCol":5,"endLine":74,"endCol":16,"covered":true}]}],"booleanDecisions":[],"calls":[]},{"id":"_ZN3iox10concurrent13LockFreeQueueIT_mE12readBufferAtERKm","name":"iox::concurrent::LockFreeQueue<T1, unsigned long>::readBufferAt(const unsigned long &)","beginLine":0,"beginCol":0,"endLine":0,"endCol":0,"covered":false,"lines":[{"line":160,"covered":true},{"line":162,"covered":true},{"line":163,"covered":true},{"line":164,"covered":true},{"line":165,"covered":true}],"statements":[],"blocks":[],"conditions":[],"branchDecisions":[],"booleanDecisions":[],"calls":[]},{"id":"_ZN3iox10concurrent13LockFreeQueueIT_mE4pushEOS2_","name":"iox::concurrent::LockFreeQueue<T1, unsigned long>::push(T1 &&)","beginLine":0,"beginCol":0,"endLine":0,"endCol":0,"covered":false,"lines":[{"line":124,"covered":true}],"statements":[],"blocks":[],"conditions":[],"branchDecisions":[],"booleanDecisions":[],"calls":[]},{"id":"_ZNK3iox10concurrent13LockFreeQueueIT_mE5emptyEv","name":"iox::concurrent::LockFreeQueue<T1, unsigned long>::empty() const","beginLine":0,"beginCol":0,"endLine":0,"endCol":0,"covered":false,"lines":[{"line":147,"covered":true}],"statements":[],"blocks":[],"conditions":[],"branchDecisions":[],"booleanDecisions":[],"calls":[]},{"id":"_ZN3iox10concurrent13LockFreeQueueIT_mE3popEv","name":"iox::concurrent::LockFreeQueue<T1, unsigned long>::pop()","beginLine":0,"beginCol":0,"endLine":0,"endCol":0,"covered":false,"lines":[{"line":130,"covered":true},{"line":132,"covered":true},{"line":134,"covered":true},{"line":137,"covered":true},{"line":139,"covered":true},{"line":141,"covered":true}],"statements":[],"blocks":[],"conditions":[],"branchDecisions":[{"beginLine":132,"beginCol":9,"endLine":132,"endCol":33,"branches":[{"beginLine":134,"beginCol":9,"endLine":134,"endCol":23,"covered":true},{"beginLine":137,"beginCol":5,"endLine":141,"endCol":18,"covered":true}]}],"booleanDecisions":[],"calls":[]},{"id":"_ZN3iox10concurrent13LockFreeQueueIT_mE13writeBufferAtIT_EEvRKmOS5_","name":"void iox::concurrent::LockFreeQueue<T1, unsigned long>::writeBufferAt<T1>(const unsigned long &, T1 &&)","beginLine":0,"beginCol":0,"endLine":0,"endCol":0,"covered":false,"lines":[{"line":176,"covered":true},{"line":172,"covered":true},{"line":173,"covered":true}],"statements":[],"blocks":[],"conditions":[],"branchDecisions":[],"booleanDecisions":[],"calls":[]},{"id":"_ZN3iox10concurrent13LockFreeQueueIT_mE8pushImplIT_EENS_8optionalIS2_EEOS5_","name":"iox::optional<T1> iox::concurrent::LockFreeQueue<T1, unsigned long>::pushImpl<T1>(T1 &&)","beginLine":0,"beginCol":0,"endLine":0,"endCol":0,"covered":false,"lines":[{"line":112,"covered":true},{"line":81,"covered":true},{"line":97,"covered":true},{"line":98,"covered":true},{"line":83,"covered":true},{"line":85,"covered":true},{"line":108,"covered":true},{"line":110,"covered":true},{"line":95,"covered":true}],"statements":[],"blocks":[],"conditions":[{"beginLine":95,"beginCol":13,"endLine":95,"endCol":42,"outcomes":[true]}],"branchDecisions":[{"beginLine":85,"beginCol":12,"endLine":85,"endCol":36,"branches":[{"beginLine":95,"beginCol":13,"endLine":95,"endCol":42,"covered":true},{"beginLine":108,"beginCol":5,"endLine":112,"endCol":24,"covered":true}]},{"beginLine":95,"beginCol":13,"endLine":95,"endCol":42,"branches":[{"beginLine":97,"beginCol":13,"endLine":98,"endCol":18,"covered":true},{"beginLine":104,"beginCol":5,"endLine":104,"endCol":5,"covered":false}]}],"booleanDecisions":[{"beginLine":95,"beginCol":13,"endLine":95,"endCol":42,"totalConditions":1,"outcomes":[{"outcome":true,"conditions":[true]}],"truthTable":[{"outcome":false,"conditions":[false]},{"outcome":true,"conditions":[true]}]}],"calls":[]},{"id":"_ZN3iox10concurrent13LockFreeQueueIT_mE4pushERKS2_","name":"iox::concurrent::LockFreeQueue<T1, unsigned long>::push(const T1 &)","beginLine":0,"beginCol":0,"endLine":0,"endCol":0,"covered":false,"lines":[{"line":118,"covered":true}],"statements":[],"blocks":[],"conditions":[],"branchDecisions":[],"booleanDecisions":[],"calls":[]},{"id":"_ZN3iox10concurrent13LockFreeQueueIT_mE7tryPushERKS2_","name":"iox::concurrent::LockFreeQueue<T1, unsigned long>::tryPush(const T1 &)","beginLine":0,"beginCol":0,"endLine":0,"endCol":0,"covered":false,"lines":[{"line":48,"covered":true},{"line":50,"covered":true},{"line":53,"covered":true},{"line":55,"covered":true},{"line":57,"covered":true},{"line":46,"covered":true}],"statements":[],"blocks":[],"conditions":[],"branchDecisions":[{"beginLine":48,"beginCol":9,"endLine":48,"endCol":33,"branches":[{"beginLine":50,"beginCol":9,"endLine":50,"endCol":21,"covered":true},{"beginLine":53,"beginCol":5,"endLine":57,"endCol":16,"covered":true}]}],"booleanDecisions":[],"calls":[]},{"id":"_ZNK3iox10concurrent13LockFreeQueueIT_mE4sizeEv","name":"iox::concurrent::LockFreeQueue<T1, unsigned long>::size() const","beginLine":0,"beginCol":0,"endLine":0,"endCol":0,"covered":false,"lines":[{"line":153,"covered":true}],"statements":[],"blocks":[],"conditions":[],"branchDecisions":[],"booleanDecisions":[],"calls":[]},{"id":"_ZN3iox10concurrent13LockFreeQueueIT_mEC9Ev","name":"iox::concurrent::LockFreeQueue<T1, unsigned long>::LockFreeQueue()","beginLine":0,"beginCol":0,"endLine":0,"endCol":0,"covered":false,"lines":[{"line":34,"covered":true}],"statements":[],"blocks":[],"conditions":[],"branchDecisions":[],"booleanDecisions":[],"calls":[]}],"checksum":"636101051","scmURL":"https://github.com/eclipse-iceoryx/iceoryx.git","scmPath":"iceoryx_hoofs/include/iceoryx_hoofs/internal/concurrent/lockfree_queue/lockfree_queue.inl","scmRevision":"669c5eb6d7869069d16f7ddc2345751efff9f7a3"}